ubtsl/__init__.py
ubtsl/__main__.py
ubtsl-0.0.1.dist-info/LICENSE
ubtsl-0.0.1.dist-info/METADATA
ubtsl-0.0.1.dist-info/WHEEL
ubtsl-0.0.1.dist-info/top_level.txt
ubtsl-0.0.1.dist-info/RECORD
