Metadata-Version: 2.1
Name: ubtsl
Version: 0.0.1
Summary: UNKNOWN
Home-page: https://github.com/LUCIT-Systems-and-Development/ubtsl
Author: LUCIT Systems and Development
Author-email: info@lucit.tech
License: MIT License
Project-URL: Author, https://www.lucit.tech
Project-URL: Issue Tracker, https://github.com/LUCIT-Systems-and-Development/ubtsl/issues
Project-URL: Chat, https://gitter.im/unicorn-binance-suite/unicorn-binance-trailing-stop-loss
Project-URL: Telegram, https://t.me/unicorndevs
Keywords: binance,
Platform: UNKNOWN
Classifier: Programming Language :: Python :: 3
Classifier: License :: OSI Approved :: MIT License
Classifier: Intended Audience :: Developers
Classifier: Intended Audience :: Financial and Insurance Industry
Classifier: Intended Audience :: Information Technology
Classifier: Intended Audience :: Science/Research
Classifier: Operating System :: OS Independent
Classifier: Topic :: Office/Business :: Financial :: Investment
Classifier: Topic :: Software Development :: Libraries :: Python Modules
Requires-Python: >=3.7.0
License-File: LICENSE
Requires-Dist: unicorn-binance-trailing-stop-loss
